README.txt
setup.cfg
setup.py
qg_utils/__init__.py
qg_utils/qg_kafka.py
qg_utils/utils.py
qg_utils.egg-info/PKG-INFO
qg_utils.egg-info/SOURCES.txt
qg_utils.egg-info/dependency_links.txt
qg_utils.egg-info/not-zip-safe
qg_utils.egg-info/top_level.txt