Metadata-Version: 1.0
Name: qg-utils
Version: 0.0.6
Summary: UNKNOWN
Home-page: https://github.com/quantumgraph/qg_utils
Author: QuantumGraph
Author-email: contact@quantumgraph.com
License: MIT
Platform: UNKNOWN
